{
  "id": 101138,
  "name": "Brandon Bass",
  "seasons": [
    {
      "season": "2005-06",
      "team": "NOK",
      "gp": 29,
      "min": 268.0,
      "pts": 68,
      "reb": 68,
      "ast": 3,
      "stl": 3,
      "blk": 7,
      "tov": 11,
      "pf": 18,
      "fgm": 28,
      "fga": 70,
      "fg3m": 0,
      "fg3a": 0,
      "ftm": 12,
      "fta": 19
    },
    {
      "season": "2006-07",
      "team": "NOK",
      "gp": 21,
      "min": 162.0,
      "pts": 42,
      "reb": 43,
      "ast": 3,
      "stl": 2,
      "blk": 3,
      "tov": 10,
      "pf": 16,
      "fgm": 15,
      "fga": 44,
      "fg3m": 0,
      "fg3a": 1,
      "ftm": 12,
      "fta": 16
    },
    {
      "season": "2007-08",
      "team": "DAL",
      "gp": 79,
      "min": 1557.0,
      "pts": 654,
      "reb": 347,
      "ast": 58,
      "stl": 22,
      "blk": 48,
      "tov": 82,
      "pf": 150,
      "fgm": 246,
      "fga": 493,
      "fg3m": 0,
      "fg3a": 4,
      "ftm": 162,
      "fta": 197
    },
    {
      "season": "2008-09",
      "team": "DAL",
      "gp": 81,
      "min": 1574.0,
      "pts": 686,
      "reb": 367,
      "ast": 43,
      "stl": 27,
      "blk": 55,
      "tov": 86,
      "pf": 140,
      "fgm": 252,
      "fga": 508,
      "fg3m": 0,
      "fg3a": 6,
      "ftm": 182,
      "fta": 210
    },
    {
      "season": "2009-10",
      "team": "ORL",
      "gp": 50,
      "min": 648.0,
      "pts": 290,
      "reb": 127,
      "ast": 19,
      "stl": 12,
      "blk": 27,
      "tov": 31,
      "pf": 69,
      "fgm": 119,
      "fga": 233,
      "fg3m": 0,
      "fg3a": 0,
      "ftm": 52,
      "fta": 63
    },
    {
      "season": "2010-11",
      "team": "ORL",
      "gp": 76,
      "min": 1980.0,
      "pts": 854,
      "reb": 424,
      "ast": 57,
      "stl": 27,
      "blk": 52,
      "tov": 97,
      "pf": 159,
      "fgm": 332,
      "fga": 645,
      "fg3m": 0,
      "fg3a": 2,
      "ftm": 190,
      "fta": 233
    },
    {
      "season": "2011-12",
      "team": "BOS",
      "gp": 59,
      "min": 1868.0,
      "pts": 738,
      "reb": 365,
      "ast": 55,
      "stl": 34,
      "blk": 54,
      "tov": 65,
      "pf": 135,
      "fgm": 303,
      "fga": 632,
      "fg3m": 0,
      "fg3a": 0,
      "ftm": 132,
      "fta": 163
    },
    {
      "season": "2012-13",
      "team": "BOS",
      "gp": 81,
      "min": 2239.0,
      "pts": 701,
      "reb": 425,
      "ast": 84,
      "stl": 44,
      "blk": 64,
      "tov": 80,
      "pf": 188,
      "fgm": 286,
      "fga": 589,
      "fg3m": 0,
      "fg3a": 2,
      "ftm": 129,
      "fta": 150
    },
    {
      "season": "2013-14",
      "team": "BOS",
      "gp": 82,
      "min": 2266.0,
      "pts": 911,
      "reb": 470,
      "ast": 87,
      "stl": 36,
      "blk": 71,
      "tov": 102,
      "pf": 190,
      "fgm": 352,
      "fga": 725,
      "fg3m": 2,
      "fg3a": 6,
      "ftm": 205,
      "fta": 239
    },
    {
      "season": "2014-15",
      "team": "BOS",
      "gp": 82,
      "min": 1929.0,
      "pts": 866,
      "reb": 398,
      "ast": 104,
      "stl": 41,
      "blk": 32,
      "tov": 83,
      "pf": 140,
      "fgm": 344,
      "fga": 683,
      "fg3m": 9,
      "fg3a": 32,
      "ftm": 169,
      "fta": 214
    },
    {
      "season": "2015-16",
      "team": "LAL",
      "gp": 66,
      "min": 1342.0,
      "pts": 473,
      "reb": 285,
      "ast": 74,
      "stl": 33,
      "blk": 55,
      "tov": 42,
      "pf": 125,
      "fgm": 174,
      "fga": 317,
      "fg3m": 0,
      "fg3a": 2,
      "ftm": 125,
      "fta": 148
    },
    {
      "season": "2016-17",
      "team": "LAC",
      "gp": 52,
      "min": 577.0,
      "pts": 292,
      "reb": 129,
      "ast": 21,
      "stl": 14,
      "blk": 11,
      "tov": 29,
      "pf": 45,
      "fgm": 107,
      "fga": 186,
      "fg3m": 1,
      "fg3a": 3,
      "ftm": 77,
      "fta": 88
    }
  ]
}