{
  "id": 1074,
  "name": "Matt Maloney",
  "seasons": [
    {
      "season": "1996-97",
      "team": "HOU",
      "gp": 82,
      "min": 2387.0,
      "pts": 767,
      "reb": 160,
      "ast": 303,
      "stl": 82,
      "blk": 1,
      "tov": 122,
      "pf": 125,
      "fgm": 271,
      "fga": 615,
      "fg3m": 154,
      "fg3a": 381,
      "ftm": 71,
      "fta": 93
    },
    {
      "season": "1997-98",
      "team": "HOU",
      "gp": 78,
      "min": 2217.0,
      "pts": 669,
      "reb": 142,
      "ast": 219,
      "stl": 62,
      "blk": 5,
      "tov": 107,
      "pf": 99,
      "fgm": 239,
      "fga": 586,
      "fg3m": 126,
      "fg3a": 346,
      "ftm": 65,
      "fta": 78
    },
    {
      "season": "1998-99",
      "team": "HOU",
      "gp": 15,
      "min": 186.0,
      "pts": 21,
      "reb": 10,
      "ast": 21,
      "stl": 4,
      "blk": 0,
      "tov": 14,
      "pf": 7,
      "fgm": 5,
      "fga": 28,
      "fg3m": 1,
      "fg3a": 15,
      "ftm": 10,
      "fta": 11
    },
    {
      "season": "1999-00",
      "team": "CHI",
      "gp": 51,
      "min": 1175.0,
      "pts": 327,
      "reb": 64,
      "ast": 138,
      "stl": 32,
      "blk": 3,
      "tov": 63,
      "pf": 42,
      "fgm": 114,
      "fga": 318,
      "fg3m": 62,
      "fg3a": 174,
      "ftm": 37,
      "fta": 45
    },
    {
      "season": "2000-01",
      "team": "ATL",
      "gp": 55,
      "min": 1403.0,
      "pts": 369,
      "reb": 117,
      "ast": 154,
      "stl": 56,
      "blk": 5,
      "tov": 70,
      "pf": 94,
      "fgm": 146,
      "fga": 348,
      "fg3m": 51,
      "fg3a": 142,
      "ftm": 26,
      "fta": 34
    },
    {
      "season": "2002-03",
      "team": "ATL",
      "gp": 14,
      "min": 103.0,
      "pts": 24,
      "reb": 7,
      "ast": 17,
      "stl": 4,
      "blk": 0,
      "tov": 5,
      "pf": 9,
      "fgm": 8,
      "fga": 25,
      "fg3m": 5,
      "fg3a": 15,
      "ftm": 3,
      "fta": 5
    }
  ]
}