{
  "id": 1629002,
  "name": "Chimezie Metu",
  "seasons": [
    {
      "season": "2018-19",
      "team": "SAS",
      "gp": 29,
      "min": 145.0,
      "pts": 51,
      "reb": 36,
      "ast": 13,
      "stl": 6,
      "blk": 2,
      "tov": 15,
      "pf": 14,
      "fgm": 19,
      "fga": 58,
      "fg3m": 0,
      "fg3a": 2,
      "ftm": 13,
      "fta": 17
    },
    {
      "season": "2019-20",
      "team": "SAS",
      "gp": 18,
      "min": 105.0,
      "pts": 58,
      "reb": 33,
      "ast": 10,
      "stl": 3,
      "blk": 6,
      "tov": 10,
      "pf": 7,
      "fgm": 24,
      "fga": 42,
      "fg3m": 0,
      "fg3a": 2,
      "ftm": 10,
      "fta": 13
    },
    {
      "season": "2020-21",
      "team": "SAC",
      "gp": 36,
      "min": 488.0,
      "pts": 226,
      "reb": 112,
      "ast": 28,
      "stl": 14,
      "blk": 18,
      "tov": 29,
      "pf": 59,
      "fgm": 91,
      "fga": 179,
      "fg3m": 13,
      "fg3a": 37,
      "ftm": 31,
      "fta": 43
    },
    {
      "season": "2021-22",
      "team": "SAC",
      "gp": 60,
      "min": 1279.0,
      "pts": 534,
      "reb": 335,
      "ast": 60,
      "stl": 51,
      "blk": 32,
      "tov": 61,
      "pf": 93,
      "fgm": 203,
      "fga": 449,
      "fg3m": 57,
      "fg3a": 186,
      "ftm": 71,
      "fta": 91
    },
    {
      "season": "2022-23",
      "team": "SAC",
      "gp": 66,
      "min": 689.0,
      "pts": 321,
      "reb": 198,
      "ast": 40,
      "stl": 22,
      "blk": 21,
      "tov": 32,
      "pf": 81,
      "fgm": 129,
      "fga": 219,
      "fg3m": 9,
      "fg3a": 38,
      "ftm": 54,
      "fta": 73
    },
    {
      "season": "2023-24",
      "team": "DET",
      "gp": 51,
      "min": 859.0,
      "pts": 332,
      "reb": 194,
      "ast": 46,
      "stl": 43,
      "blk": 16,
      "tov": 52,
      "pf": 71,
      "fgm": 123,
      "fga": 244,
      "fg3m": 28,
      "fg3a": 94,
      "ftm": 58,
      "fta": 64
    }
  ]
}