{
  "id": 1630228,
  "name": "Jonathan Kuminga",
  "seasons": [
    {
      "season": "2021-22",
      "team": "GSW",
      "gp": 70,
      "min": 1185.0,
      "pts": 652,
      "reb": 234,
      "ast": 64,
      "stl": 31,
      "blk": 22,
      "tov": 74,
      "pf": 146,
      "fgm": 236,
      "fga": 460,
      "fg3m": 50,
      "fg3a": 149,
      "ftm": 130,
      "fta": 190
    },
    {
      "season": "2022-23",
      "team": "GSW",
      "gp": 67,
      "min": 1394.0,
      "pts": 666,
      "reb": 231,
      "ast": 125,
      "stl": 41,
      "blk": 31,
      "tov": 95,
      "pf": 157,
      "fgm": 261,
      "fga": 497,
      "fg3m": 54,
      "fg3a": 146,
      "ftm": 90,
      "fta": 138
    },
    {
      "season": "2023-24",
      "team": "GSW",
      "gp": 74,
      "min": 1949.0,
      "pts": 1188,
      "reb": 355,
      "ast": 163,
      "stl": 55,
      "blk": 36,
      "tov": 122,
      "pf": 169,
      "fgm": 456,
      "fga": 862,
      "fg3m": 53,
      "fg3a": 165,
      "ftm": 223,
      "fta": 299
    },
    {
      "season": "2024-25",
      "team": "GSW",
      "gp": 47,
      "min": 1144.0,
      "pts": 719,
      "reb": 217,
      "ast": 104,
      "stl": 38,
      "blk": 21,
      "tov": 71,
      "pf": 90,
      "fgm": 258,
      "fga": 568,
      "fg3m": 46,
      "fg3a": 151,
      "ftm": 157,
      "fta": 235
    },
    {
      "season": "2025-26",
      "team": "ATL",
      "gp": 36,
      "min": 831.0,
      "pts": 438,
      "reb": 202,
      "ast": 83,
      "stl": 22,
      "blk": 11,
      "tov": 67,
      "pf": 55,
      "fgm": 157,
      "fga": 339,
      "fg3m": 35,
      "fg3a": 105,
      "ftm": 89,
      "fta": 123
    }
  ]
}