{
  "id": 1630549,
  "name": "Day'Ron Sharpe",
  "seasons": [
    {
      "season": "2021-22",
      "team": "BKN",
      "gp": 32,
      "min": 391.0,
      "pts": 198,
      "reb": 160,
      "ast": 17,
      "stl": 10,
      "blk": 15,
      "tov": 30,
      "pf": 60,
      "fgm": 86,
      "fga": 149,
      "fg3m": 2,
      "fg3a": 7,
      "ftm": 24,
      "fta": 41
    },
    {
      "season": "2022-23",
      "team": "BKN",
      "gp": 48,
      "min": 553.0,
      "pts": 227,
      "reb": 200,
      "ast": 37,
      "stl": 15,
      "blk": 32,
      "tov": 42,
      "pf": 89,
      "fgm": 93,
      "fga": 171,
      "fg3m": 6,
      "fg3a": 11,
      "ftm": 35,
      "fta": 55
    },
    {
      "season": "2023-24",
      "team": "BKN",
      "gp": 61,
      "min": 921.0,
      "pts": 415,
      "reb": 389,
      "ast": 85,
      "stl": 24,
      "blk": 44,
      "tov": 70,
      "pf": 131,
      "fgm": 168,
      "fga": 294,
      "fg3m": 4,
      "fg3a": 15,
      "ftm": 75,
      "fta": 123
    },
    {
      "season": "2024-25",
      "team": "BKN",
      "gp": 50,
      "min": 907.0,
      "pts": 397,
      "reb": 330,
      "ast": 91,
      "stl": 41,
      "blk": 42,
      "tov": 63,
      "pf": 113,
      "fgm": 165,
      "fga": 317,
      "fg3m": 11,
      "fg3a": 45,
      "ftm": 56,
      "fta": 74
    },
    {
      "season": "2025-26",
      "team": "BKN",
      "gp": 62,
      "min": 1160.0,
      "pts": 540,
      "reb": 413,
      "ast": 145,
      "stl": 67,
      "blk": 26,
      "tov": 106,
      "pf": 147,
      "fgm": 214,
      "fga": 356,
      "fg3m": 9,
      "fg3a": 39,
      "ftm": 103,
      "fta": 152
    }
  ]
}