{
  "id": 201141,
  "name": "Greg Oden",
  "seasons": [
    {
      "season": "2008-09",
      "team": "POR",
      "gp": 61,
      "min": 1314.0,
      "pts": 540,
      "reb": 424,
      "ast": 31,
      "stl": 25,
      "blk": 69,
      "tov": 87,
      "pf": 238,
      "fgm": 198,
      "fga": 351,
      "fg3m": 0,
      "fg3a": 0,
      "ftm": 144,
      "fta": 226
    },
    {
      "season": "2009-10",
      "team": "POR",
      "gp": 21,
      "min": 502.0,
      "pts": 233,
      "reb": 178,
      "ast": 19,
      "stl": 8,
      "blk": 48,
      "tov": 39,
      "pf": 84,
      "fgm": 92,
      "fga": 152,
      "fg3m": 0,
      "fg3a": 0,
      "ftm": 49,
      "fta": 64
    },
    {
      "season": "2013-14",
      "team": "MIA",
      "gp": 23,
      "min": 212.0,
      "pts": 67,
      "reb": 54,
      "ast": 1,
      "stl": 7,
      "blk": 13,
      "tov": 12,
      "pf": 52,
      "fgm": 27,
      "fga": 49,
      "fg3m": 0,
      "fg3a": 0,
      "ftm": 13,
      "fta": 23
    }
  ]
}