{
  "id": 202336,
  "name": "Larry Sanders",
  "seasons": [
    {
      "season": "2010-11",
      "team": "MIL",
      "gp": 60,
      "min": 872.0,
      "pts": 260,
      "reb": 178,
      "ast": 16,
      "stl": 22,
      "blk": 72,
      "tov": 38,
      "pf": 117,
      "fgm": 116,
      "fga": 268,
      "fg3m": 0,
      "fg3a": 0,
      "ftm": 28,
      "fta": 50
    },
    {
      "season": "2011-12",
      "team": "MIL",
      "gp": 52,
      "min": 643.0,
      "pts": 186,
      "reb": 160,
      "ast": 33,
      "stl": 32,
      "blk": 76,
      "tov": 43,
      "pf": 133,
      "fgm": 84,
      "fga": 184,
      "fg3m": 0,
      "fg3a": 2,
      "ftm": 18,
      "fta": 38
    },
    {
      "season": "2012-13",
      "team": "MIL",
      "gp": 71,
      "min": 1937.0,
      "pts": 696,
      "reb": 672,
      "ast": 83,
      "stl": 53,
      "blk": 201,
      "tov": 87,
      "pf": 233,
      "fgm": 306,
      "fga": 605,
      "fg3m": 0,
      "fg3a": 2,
      "ftm": 84,
      "fta": 136
    },
    {
      "season": "2013-14",
      "team": "MIL",
      "gp": 23,
      "min": 584.0,
      "pts": 178,
      "reb": 165,
      "ast": 19,
      "stl": 18,
      "blk": 40,
      "tov": 26,
      "pf": 74,
      "fgm": 76,
      "fga": 162,
      "fg3m": 0,
      "fg3a": 1,
      "ftm": 26,
      "fta": 55
    },
    {
      "season": "2014-15",
      "team": "MIL",
      "gp": 27,
      "min": 586.0,
      "pts": 196,
      "reb": 166,
      "ast": 23,
      "stl": 26,
      "blk": 39,
      "tov": 28,
      "pf": 104,
      "fgm": 86,
      "fga": 172,
      "fg3m": 0,
      "fg3a": 0,
      "ftm": 24,
      "fta": 48
    },
    {
      "season": "2016-17",
      "team": "CLE",
      "gp": 5,
      "min": 13.0,
      "pts": 4,
      "reb": 4,
      "ast": 0,
      "stl": 1,
      "blk": 1,
      "tov": 2,
      "pf": 5,
      "fgm": 1,
      "fga": 4,
      "fg3m": 0,
      "fg3a": 0,
      "ftm": 2,
      "fta": 2
    }
  ]
}