{
  "id": 202329,
  "name": "Al-Farouq Aminu",
  "seasons": [
    {
      "season": "2010-11",
      "team": "LAC",
      "gp": 81,
      "min": 1452.0,
      "pts": 457,
      "reb": 267,
      "ast": 60,
      "stl": 59,
      "blk": 25,
      "tov": 103,
      "pf": 121,
      "fgm": 160,
      "fga": 406,
      "fg3m": 45,
      "fg3a": 143,
      "ftm": 92,
      "fta": 119
    },
    {
      "season": "2011-12",
      "team": "NOH",
      "gp": 66,
      "min": 1477.0,
      "pts": 399,
      "reb": 308,
      "ast": 66,
      "stl": 59,
      "blk": 34,
      "tov": 91,
      "pf": 136,
      "fgm": 150,
      "fga": 365,
      "fg3m": 13,
      "fg3a": 47,
      "ftm": 86,
      "fta": 114
    },
    {
      "season": "2012-13",
      "team": "NOH",
      "gp": 76,
      "min": 2066.0,
      "pts": 555,
      "reb": 585,
      "ast": 103,
      "stl": 92,
      "blk": 51,
      "tov": 116,
      "pf": 153,
      "fgm": 225,
      "fga": 474,
      "fg3m": 4,
      "fg3a": 19,
      "ftm": 101,
      "fta": 137
    },
    {
      "season": "2013-14",
      "team": "NOP",
      "gp": 80,
      "min": 2045.0,
      "pts": 572,
      "reb": 496,
      "ast": 114,
      "stl": 82,
      "blk": 38,
      "tov": 88,
      "pf": 147,
      "fgm": 234,
      "fga": 494,
      "fg3m": 13,
      "fg3a": 48,
      "ftm": 91,
      "fta": 137
    },
    {
      "season": "2014-15",
      "team": "DAL",
      "gp": 74,
      "min": 1366.0,
      "pts": 412,
      "reb": 342,
      "ast": 59,
      "stl": 70,
      "blk": 62,
      "tov": 55,
      "pf": 137,
      "fgm": 147,
      "fga": 357,
      "fg3m": 34,
      "fg3a": 124,
      "ftm": 84,
      "fta": 118
    },
    {
      "season": "2015-16",
      "team": "POR",
      "gp": 82,
      "min": 2341.0,
      "pts": 839,
      "reb": 499,
      "ast": 138,
      "stl": 72,
      "blk": 53,
      "tov": 120,
      "pf": 171,
      "fgm": 299,
      "fga": 719,
      "fg3m": 126,
      "fg3a": 349,
      "ftm": 115,
      "fta": 156
    },
    {
      "season": "2016-17",
      "team": "POR",
      "gp": 61,
      "min": 1773.0,
      "pts": 532,
      "reb": 451,
      "ast": 99,
      "stl": 60,
      "blk": 44,
      "tov": 94,
      "pf": 102,
      "fgm": 183,
      "fga": 466,
      "fg3m": 70,
      "fg3a": 212,
      "ftm": 96,
      "fta": 136
    },
    {
      "season": "2017-18",
      "team": "POR",
      "gp": 69,
      "min": 2072.0,
      "pts": 644,
      "reb": 525,
      "ast": 84,
      "stl": 79,
      "blk": 40,
      "tov": 79,
      "pf": 136,
      "fgm": 230,
      "fga": 582,
      "fg3m": 125,
      "fg3a": 339,
      "ftm": 59,
      "fta": 80
    },
    {
      "season": "2018-19",
      "team": "POR",
      "gp": 81,
      "min": 2292.0,
      "pts": 760,
      "reb": 610,
      "ast": 104,
      "stl": 68,
      "blk": 33,
      "tov": 72,
      "pf": 143,
      "fgm": 257,
      "fga": 593,
      "fg3m": 96,
      "fg3a": 280,
      "ftm": 150,
      "fta": 173
    },
    {
      "season": "2019-20",
      "team": "ORL",
      "gp": 18,
      "min": 380.0,
      "pts": 78,
      "reb": 87,
      "ast": 21,
      "stl": 18,
      "blk": 8,
      "tov": 17,
      "pf": 27,
      "fgm": 25,
      "fga": 86,
      "fg3m": 9,
      "fg3a": 36,
      "ftm": 19,
      "fta": 29
    },
    {
      "season": "2020-21",
      "team": "CHI",
      "gp": 23,
      "min": 434.0,
      "pts": 102,
      "reb": 110,
      "ast": 31,
      "stl": 19,
      "blk": 9,
      "tov": 28,
      "pf": 29,
      "fgm": 38,
      "fga": 99,
      "fg3m": 8,
      "fg3a": 37,
      "ftm": 18,
      "fta": 22
    }
  ]
}