{
  "id": 203081,
  "name": "Damian Lillard",
  "seasons": [
    {
      "season": "2012-13",
      "team": "POR",
      "gp": 82,
      "min": 3167.0,
      "pts": 1562,
      "reb": 257,
      "ast": 531,
      "stl": 74,
      "blk": 19,
      "tov": 243,
      "pf": 172,
      "fgm": 553,
      "fga": 1288,
      "fg3m": 185,
      "fg3a": 503,
      "ftm": 271,
      "fta": 321
    },
    {
      "season": "2013-14",
      "team": "POR",
      "gp": 82,
      "min": 2937.0,
      "pts": 1695,
      "reb": 288,
      "ast": 457,
      "stl": 64,
      "blk": 22,
      "tov": 193,
      "pf": 197,
      "fgm": 553,
      "fga": 1304,
      "fg3m": 218,
      "fg3a": 554,
      "ftm": 371,
      "fta": 426
    },
    {
      "season": "2014-15",
      "team": "POR",
      "gp": 82,
      "min": 2925.0,
      "pts": 1720,
      "reb": 378,
      "ast": 507,
      "stl": 97,
      "blk": 21,
      "tov": 222,
      "pf": 164,
      "fgm": 590,
      "fga": 1360,
      "fg3m": 196,
      "fg3a": 572,
      "ftm": 344,
      "fta": 398
    },
    {
      "season": "2015-16",
      "team": "POR",
      "gp": 75,
      "min": 2676.0,
      "pts": 1879,
      "reb": 302,
      "ast": 512,
      "stl": 65,
      "blk": 28,
      "tov": 242,
      "pf": 165,
      "fgm": 618,
      "fga": 1474,
      "fg3m": 229,
      "fg3a": 610,
      "ftm": 414,
      "fta": 464
    },
    {
      "season": "2016-17",
      "team": "POR",
      "gp": 75,
      "min": 2693.0,
      "pts": 2024,
      "reb": 368,
      "ast": 440,
      "stl": 68,
      "blk": 20,
      "tov": 197,
      "pf": 152,
      "fgm": 661,
      "fga": 1488,
      "fg3m": 214,
      "fg3a": 579,
      "ftm": 488,
      "fta": 545
    },
    {
      "season": "2017-18",
      "team": "POR",
      "gp": 73,
      "min": 2670.0,
      "pts": 1962,
      "reb": 325,
      "ast": 481,
      "stl": 77,
      "blk": 27,
      "tov": 206,
      "pf": 117,
      "fgm": 621,
      "fga": 1415,
      "fg3m": 227,
      "fg3a": 629,
      "ftm": 493,
      "fta": 538
    },
    {
      "season": "2018-19",
      "team": "POR",
      "gp": 80,
      "min": 2838.0,
      "pts": 2067,
      "reb": 371,
      "ast": 551,
      "stl": 88,
      "blk": 34,
      "tov": 212,
      "pf": 148,
      "fgm": 681,
      "fga": 1533,
      "fg3m": 237,
      "fg3a": 643,
      "ftm": 468,
      "fta": 513
    },
    {
      "season": "2019-20",
      "team": "POR",
      "gp": 66,
      "min": 2474.0,
      "pts": 1978,
      "reb": 284,
      "ast": 530,
      "stl": 70,
      "blk": 22,
      "tov": 194,
      "pf": 114,
      "fgm": 624,
      "fga": 1349,
      "fg3m": 270,
      "fg3a": 674,
      "ftm": 460,
      "fta": 518
    },
    {
      "season": "2020-21",
      "team": "POR",
      "gp": 67,
      "min": 2398.0,
      "pts": 1928,
      "reb": 283,
      "ast": 505,
      "stl": 62,
      "blk": 17,
      "tov": 203,
      "pf": 102,
      "fgm": 602,
      "fga": 1334,
      "fg3m": 275,
      "fg3a": 704,
      "ftm": 449,
      "fta": 484
    },
    {
      "season": "2021-22",
      "team": "POR",
      "gp": 29,
      "min": 1056.0,
      "pts": 695,
      "reb": 120,
      "ast": 212,
      "stl": 17,
      "blk": 11,
      "tov": 83,
      "pf": 37,
      "fgm": 222,
      "fga": 552,
      "fg3m": 92,
      "fg3a": 284,
      "ftm": 159,
      "fta": 181
    },
    {
      "season": "2022-23",
      "team": "POR",
      "gp": 58,
      "min": 2107.0,
      "pts": 1866,
      "reb": 277,
      "ast": 425,
      "stl": 50,
      "blk": 18,
      "tov": 191,
      "pf": 109,
      "fgm": 556,
      "fga": 1202,
      "fg3m": 244,
      "fg3a": 658,
      "ftm": 510,
      "fta": 558
    },
    {
      "season": "2023-24",
      "team": "MIL",
      "gp": 73,
      "min": 2578.0,
      "pts": 1775,
      "reb": 320,
      "ast": 508,
      "stl": 72,
      "blk": 18,
      "tov": 193,
      "pf": 134,
      "fgm": 541,
      "fga": 1277,
      "fg3m": 220,
      "fg3a": 622,
      "ftm": 473,
      "fta": 514
    },
    {
      "season": "2024-25",
      "team": "MIL",
      "gp": 58,
      "min": 2093.0,
      "pts": 1447,
      "reb": 272,
      "ast": 410,
      "stl": 70,
      "blk": 10,
      "tov": 162,
      "pf": 97,
      "fgm": 444,
      "fga": 992,
      "fg3m": 197,
      "fg3a": 524,
      "ftm": 362,
      "fta": 393
    }
  ]
}