{
  "id": 203156,
  "name": "Henry Sims",
  "seasons": [
    {
      "season": "2012-13",
      "team": "NOH",
      "gp": 2,
      "min": 5.0,
      "pts": 4,
      "reb": 2,
      "ast": 0,
      "stl": 0,
      "blk": 0,
      "tov": 1,
      "pf": 1,
      "fgm": 2,
      "fga": 3,
      "fg3m": 0,
      "fg3a": 0,
      "ftm": 0,
      "fta": 0
    },
    {
      "season": "2013-14",
      "team": "PHI",
      "gp": 46,
      "min": 875.0,
      "pts": 350,
      "reb": 237,
      "ast": 52,
      "stl": 28,
      "blk": 20,
      "tov": 41,
      "pf": 116,
      "fgm": 130,
      "fga": 274,
      "fg3m": 0,
      "fg3a": 1,
      "ftm": 90,
      "fta": 121
    },
    {
      "season": "2014-15",
      "team": "PHI",
      "gp": 73,
      "min": 1399.0,
      "pts": 586,
      "reb": 359,
      "ast": 79,
      "stl": 39,
      "blk": 30,
      "tov": 99,
      "pf": 135,
      "fgm": 238,
      "fga": 502,
      "fg3m": 4,
      "fg3a": 22,
      "ftm": 106,
      "fta": 137
    },
    {
      "season": "2015-16",
      "team": "BKN",
      "gp": 14,
      "min": 263.0,
      "pts": 91,
      "reb": 72,
      "ast": 9,
      "stl": 9,
      "blk": 14,
      "tov": 12,
      "pf": 37,
      "fgm": 33,
      "fga": 77,
      "fg3m": 0,
      "fg3a": 0,
      "ftm": 25,
      "fta": 30
    }
  ]
}