{
  "id": 229,
  "name": "James Edwards",
  "seasons": [
    {
      "season": "1977-78",
      "team": "IND",
      "gp": 83,
      "min": 2405.0,
      "pts": 1262,
      "reb": 615,
      "ast": 85,
      "stl": 53,
      "blk": 78,
      "tov": 169,
      "pf": 322,
      "fgm": 495,
      "fga": 1093,
      "fg3m": 0,
      "fg3a": 0,
      "ftm": 272,
      "fta": 421
    },
    {
      "season": "1978-79",
      "team": "IND",
      "gp": 82,
      "min": 2546.0,
      "pts": 1366,
      "reb": 693,
      "ast": 92,
      "stl": 60,
      "blk": 109,
      "tov": 162,
      "pf": 363,
      "fgm": 534,
      "fga": 1065,
      "fg3m": 0,
      "fg3a": 0,
      "ftm": 298,
      "fta": 441
    },
    {
      "season": "1979-80",
      "team": "IND",
      "gp": 82,
      "min": 2314.0,
      "pts": 1287,
      "reb": 578,
      "ast": 127,
      "stl": 55,
      "blk": 104,
      "tov": 131,
      "pf": 324,
      "fgm": 528,
      "fga": 1032,
      "fg3m": 0,
      "fg3a": 1,
      "ftm": 231,
      "fta": 339
    },
    {
      "season": "1980-81",
      "team": "IND",
      "gp": 81,
      "min": 2375.0,
      "pts": 1266,
      "reb": 571,
      "ast": 212,
      "stl": 32,
      "blk": 128,
      "tov": 164,
      "pf": 304,
      "fgm": 511,
      "fga": 1004,
      "fg3m": 0,
      "fg3a": 3,
      "ftm": 244,
      "fta": 347
    },
    {
      "season": "1981-82",
      "team": "CLE",
      "gp": 77,
      "min": 2539.0,
      "pts": 1288,
      "reb": 581,
      "ast": 123,
      "stl": 24,
      "blk": 117,
      "tov": 162,
      "pf": 347,
      "fgm": 528,
      "fga": 1033,
      "fg3m": 0,
      "fg3a": 4,
      "ftm": 232,
      "fta": 339
    },
    {
      "season": "1982-83",
      "team": "PHX",
      "gp": 31,
      "min": 667.0,
      "pts": 325,
      "reb": 155,
      "ast": 40,
      "stl": 12,
      "blk": 19,
      "tov": 49,
      "pf": 110,
      "fgm": 128,
      "fga": 263,
      "fg3m": 0,
      "fg3a": 0,
      "ftm": 69,
      "fta": 108
    },
    {
      "season": "1983-84",
      "team": "PHX",
      "gp": 72,
      "min": 1897.0,
      "pts": 1059,
      "reb": 348,
      "ast": 184,
      "stl": 23,
      "blk": 30,
      "tov": 140,
      "pf": 254,
      "fgm": 438,
      "fga": 817,
      "fg3m": 0,
      "fg3a": 1,
      "ftm": 183,
      "fta": 254
    },
    {
      "season": "1984-85",
      "team": "PHX",
      "gp": 70,
      "min": 1787.0,
      "pts": 1044,
      "reb": 387,
      "ast": 153,
      "stl": 26,
      "blk": 52,
      "tov": 162,
      "pf": 237,
      "fgm": 384,
      "fga": 766,
      "fg3m": 0,
      "fg3a": 3,
      "ftm": 276,
      "fta": 370
    },
    {
      "season": "1985-86",
      "team": "PHX",
      "gp": 52,
      "min": 1314.0,
      "pts": 848,
      "reb": 301,
      "ast": 74,
      "stl": 23,
      "blk": 29,
      "tov": 128,
      "pf": 200,
      "fgm": 318,
      "fga": 587,
      "fg3m": 0,
      "fg3a": 0,
      "ftm": 212,
      "fta": 302
    },
    {
      "season": "1986-87",
      "team": "PHX",
      "gp": 14,
      "min": 304.0,
      "pts": 168,
      "reb": 60,
      "ast": 19,
      "stl": 6,
      "blk": 7,
      "tov": 15,
      "pf": 42,
      "fgm": 57,
      "fga": 110,
      "fg3m": 0,
      "fg3a": 0,
      "ftm": 54,
      "fta": 70
    },
    {
      "season": "1987-88",
      "team": "DET",
      "gp": 69,
      "min": 1705.0,
      "pts": 814,
      "reb": 412,
      "ast": 78,
      "stl": 16,
      "blk": 37,
      "tov": 130,
      "pf": 216,
      "fgm": 302,
      "fga": 643,
      "fg3m": 0,
      "fg3a": 1,
      "ftm": 210,
      "fta": 321
    },
    {
      "season": "1988-89",
      "team": "DET",
      "gp": 76,
      "min": 1254.0,
      "pts": 555,
      "reb": 231,
      "ast": 49,
      "stl": 11,
      "blk": 31,
      "tov": 72,
      "pf": 226,
      "fgm": 211,
      "fga": 422,
      "fg3m": 0,
      "fg3a": 2,
      "ftm": 133,
      "fta": 194
    },
    {
      "season": "1989-90",
      "team": "DET",
      "gp": 82,
      "min": 2283.0,
      "pts": 1189,
      "reb": 345,
      "ast": 63,
      "stl": 23,
      "blk": 37,
      "tov": 133,
      "pf": 295,
      "fgm": 462,
      "fga": 928,
      "fg3m": 0,
      "fg3a": 3,
      "ftm": 265,
      "fta": 354
    },
    {
      "season": "1990-91",
      "team": "DET",
      "gp": 72,
      "min": 1903.0,
      "pts": 982,
      "reb": 277,
      "ast": 65,
      "stl": 12,
      "blk": 30,
      "tov": 126,
      "pf": 249,
      "fgm": 383,
      "fga": 792,
      "fg3m": 1,
      "fg3a": 2,
      "ftm": 215,
      "fta": 295
    },
    {
      "season": "1991-92",
      "team": "LAC",
      "gp": 72,
      "min": 1437.0,
      "pts": 698,
      "reb": 202,
      "ast": 53,
      "stl": 24,
      "blk": 33,
      "tov": 72,
      "pf": 236,
      "fgm": 250,
      "fga": 538,
      "fg3m": 0,
      "fg3a": 1,
      "ftm": 198,
      "fta": 271
    },
    {
      "season": "1992-93",
      "team": "LAL",
      "gp": 52,
      "min": 617.0,
      "pts": 328,
      "reb": 100,
      "ast": 41,
      "stl": 10,
      "blk": 7,
      "tov": 51,
      "pf": 122,
      "fgm": 122,
      "fga": 270,
      "fg3m": 0,
      "fg3a": 0,
      "ftm": 84,
      "fta": 118
    },
    {
      "season": "1993-94",
      "team": "LAL",
      "gp": 45,
      "min": 469.0,
      "pts": 210,
      "reb": 65,
      "ast": 22,
      "stl": 4,
      "blk": 3,
      "tov": 30,
      "pf": 90,
      "fgm": 78,
      "fga": 168,
      "fg3m": 0,
      "fg3a": 0,
      "ftm": 54,
      "fta": 79
    },
    {
      "season": "1994-95",
      "team": "POR",
      "gp": 28,
      "min": 266.0,
      "pts": 75,
      "reb": 43,
      "ast": 8,
      "stl": 5,
      "blk": 8,
      "tov": 14,
      "pf": 44,
      "fgm": 32,
      "fga": 83,
      "fg3m": 0,
      "fg3a": 0,
      "ftm": 11,
      "fta": 17
    },
    {
      "season": "1995-96",
      "team": "CHI",
      "gp": 28,
      "min": 274.0,
      "pts": 98,
      "reb": 40,
      "ast": 11,
      "stl": 1,
      "blk": 8,
      "tov": 21,
      "pf": 61,
      "fgm": 41,
      "fga": 110,
      "fg3m": 0,
      "fg3a": 0,
      "ftm": 16,
      "fta": 26
    }
  ]
}