{
  "id": 76005,
  "name": "Tom Abernethy",
  "seasons": [
    {
      "season": "1976-77",
      "team": "LAL",
      "gp": 70,
      "min": 1378.0,
      "pts": 439,
      "reb": 291,
      "ast": 98,
      "stl": 49,
      "blk": 10,
      "tov": 0,
      "pf": 118,
      "fgm": 169,
      "fga": 349,
      "fg3m": 0,
      "fg3a": 0,
      "ftm": 101,
      "fta": 134
    },
    {
      "season": "1977-78",
      "team": "LAL",
      "gp": 73,
      "min": 1317.0,
      "pts": 493,
      "reb": 265,
      "ast": 101,
      "stl": 55,
      "blk": 22,
      "tov": 50,
      "pf": 122,
      "fgm": 201,
      "fga": 404,
      "fg3m": 0,
      "fg3a": 0,
      "ftm": 91,
      "fta": 111
    },
    {
      "season": "1978-79",
      "team": "GOS",
      "gp": 70,
      "min": 1219.0,
      "pts": 422,
      "reb": 216,
      "ast": 79,
      "stl": 39,
      "blk": 13,
      "tov": 32,
      "pf": 133,
      "fgm": 176,
      "fga": 342,
      "fg3m": 0,
      "fg3a": 0,
      "ftm": 70,
      "fta": 94
    },
    {
      "season": "1979-80",
      "team": "GOS",
      "gp": 67,
      "min": 1222.0,
      "pts": 362,
      "reb": 191,
      "ast": 87,
      "stl": 35,
      "blk": 12,
      "tov": 39,
      "pf": 118,
      "fgm": 153,
      "fga": 318,
      "fg3m": 0,
      "fg3a": 1,
      "ftm": 56,
      "fta": 82
    },
    {
      "season": "1980-81",
      "team": "IND",
      "gp": 39,
      "min": 298.0,
      "pts": 63,
      "reb": 48,
      "ast": 19,
      "stl": 7,
      "blk": 3,
      "tov": 8,
      "pf": 34,
      "fgm": 25,
      "fga": 59,
      "fg3m": 0,
      "fg3a": 1,
      "ftm": 13,
      "fta": 22
    }
  ]
}