{
  "id": 76170,
  "name": "Otis Birdsong",
  "seasons": [
    {
      "season": "1977-78",
      "team": "KCK",
      "gp": 73,
      "min": 1878.0,
      "pts": 1156,
      "reb": 175,
      "ast": 174,
      "stl": 74,
      "blk": 12,
      "tov": 145,
      "pf": 179,
      "fgm": 470,
      "fga": 955,
      "fg3m": 0,
      "fg3a": 0,
      "ftm": 216,
      "fta": 310
    },
    {
      "season": "1978-79",
      "team": "KCK",
      "gp": 82,
      "min": 2839.0,
      "pts": 1778,
      "reb": 354,
      "ast": 281,
      "stl": 125,
      "blk": 17,
      "tov": 200,
      "pf": 255,
      "fgm": 741,
      "fga": 1456,
      "fg3m": 0,
      "fg3a": 0,
      "ftm": 296,
      "fta": 408
    },
    {
      "season": "1979-80",
      "team": "KCK",
      "gp": 82,
      "min": 2885.0,
      "pts": 1858,
      "reb": 331,
      "ast": 202,
      "stl": 136,
      "blk": 22,
      "tov": 179,
      "pf": 226,
      "fgm": 781,
      "fga": 1546,
      "fg3m": 10,
      "fg3a": 36,
      "ftm": 286,
      "fta": 412
    },
    {
      "season": "1980-81",
      "team": "KCK",
      "gp": 71,
      "min": 2593.0,
      "pts": 1747,
      "reb": 258,
      "ast": 233,
      "stl": 93,
      "blk": 18,
      "tov": 173,
      "pf": 172,
      "fgm": 710,
      "fga": 1306,
      "fg3m": 10,
      "fg3a": 35,
      "ftm": 317,
      "fta": 455
    },
    {
      "season": "1981-82",
      "team": "NJN",
      "gp": 37,
      "min": 1025.0,
      "pts": 524,
      "reb": 97,
      "ast": 124,
      "stl": 30,
      "blk": 5,
      "tov": 64,
      "pf": 74,
      "fgm": 225,
      "fga": 480,
      "fg3m": 0,
      "fg3a": 10,
      "ftm": 74,
      "fta": 127
    },
    {
      "season": "1982-83",
      "team": "NJN",
      "gp": 62,
      "min": 1885.0,
      "pts": 936,
      "reb": 150,
      "ast": 239,
      "stl": 85,
      "blk": 16,
      "tov": 114,
      "pf": 155,
      "fgm": 426,
      "fga": 834,
      "fg3m": 2,
      "fg3a": 6,
      "ftm": 82,
      "fta": 145
    },
    {
      "season": "1983-84",
      "team": "NJN",
      "gp": 69,
      "min": 2168.0,
      "pts": 1365,
      "reb": 170,
      "ast": 266,
      "stl": 86,
      "blk": 17,
      "tov": 170,
      "pf": 180,
      "fgm": 583,
      "fga": 1147,
      "fg3m": 5,
      "fg3a": 20,
      "ftm": 194,
      "fta": 319
    },
    {
      "season": "1984-85",
      "team": "NJN",
      "gp": 56,
      "min": 1842.0,
      "pts": 1155,
      "reb": 148,
      "ast": 232,
      "stl": 84,
      "blk": 7,
      "tov": 117,
      "pf": 145,
      "fgm": 495,
      "fga": 968,
      "fg3m": 4,
      "fg3a": 21,
      "ftm": 161,
      "fta": 259
    },
    {
      "season": "1985-86",
      "team": "NJN",
      "gp": 77,
      "min": 2395.0,
      "pts": 1214,
      "reb": 202,
      "ast": 261,
      "stl": 85,
      "blk": 17,
      "tov": 179,
      "pf": 228,
      "fgm": 542,
      "fga": 1056,
      "fg3m": 8,
      "fg3a": 22,
      "ftm": 122,
      "fta": 210
    },
    {
      "season": "1986-87",
      "team": "NJN",
      "gp": 7,
      "min": 127.0,
      "pts": 44,
      "reb": 7,
      "ast": 17,
      "stl": 3,
      "blk": 0,
      "tov": 9,
      "pf": 16,
      "fgm": 19,
      "fga": 42,
      "fg3m": 0,
      "fg3a": 1,
      "ftm": 6,
      "fta": 9
    },
    {
      "season": "1987-88",
      "team": "NJN",
      "gp": 67,
      "min": 1882.0,
      "pts": 730,
      "reb": 167,
      "ast": 222,
      "stl": 54,
      "blk": 11,
      "tov": 129,
      "pf": 143,
      "fgm": 337,
      "fga": 736,
      "fg3m": 9,
      "fg3a": 25,
      "ftm": 47,
      "fta": 92
    },
    {
      "season": "1988-89",
      "team": "BOS",
      "gp": 13,
      "min": 108.0,
      "pts": 37,
      "reb": 13,
      "ast": 9,
      "stl": 3,
      "blk": 1,
      "tov": 12,
      "pf": 10,
      "fgm": 18,
      "fga": 36,
      "fg3m": 1,
      "fg3a": 3,
      "ftm": 0,
      "fta": 2
    }
  ]
}