{
  "id": 76252,
  "name": "Junior Bridgeman",
  "seasons": [
    {
      "season": "1975-76",
      "team": "MIL",
      "gp": 81,
      "min": 1646.0,
      "pts": 700,
      "reb": 294,
      "ast": 157,
      "stl": 52,
      "blk": 21,
      "tov": 0,
      "pf": 235,
      "fgm": 286,
      "fga": 651,
      "fg3m": 0,
      "fg3a": 0,
      "ftm": 128,
      "fta": 161
    },
    {
      "season": "1976-77",
      "team": "MIL",
      "gp": 82,
      "min": 2410.0,
      "pts": 1179,
      "reb": 416,
      "ast": 205,
      "stl": 82,
      "blk": 26,
      "tov": 0,
      "pf": 221,
      "fgm": 491,
      "fga": 1094,
      "fg3m": 0,
      "fg3a": 0,
      "ftm": 197,
      "fta": 228
    },
    {
      "season": "1977-78",
      "team": "MIL",
      "gp": 82,
      "min": 1876.0,
      "pts": 1118,
      "reb": 290,
      "ast": 175,
      "stl": 72,
      "blk": 30,
      "tov": 176,
      "pf": 202,
      "fgm": 476,
      "fga": 947,
      "fg3m": 0,
      "fg3a": 0,
      "ftm": 166,
      "fta": 205
    },
    {
      "season": "1978-79",
      "team": "MIL",
      "gp": 82,
      "min": 1963.0,
      "pts": 1269,
      "reb": 297,
      "ast": 163,
      "stl": 88,
      "blk": 41,
      "tov": 138,
      "pf": 184,
      "fgm": 540,
      "fga": 1067,
      "fg3m": 0,
      "fg3a": 0,
      "ftm": 189,
      "fta": 228
    },
    {
      "season": "1979-80",
      "team": "MIL",
      "gp": 81,
      "min": 2316.0,
      "pts": 1423,
      "reb": 301,
      "ast": 237,
      "stl": 94,
      "blk": 20,
      "tov": 172,
      "pf": 216,
      "fgm": 594,
      "fga": 1243,
      "fg3m": 5,
      "fg3a": 27,
      "ftm": 230,
      "fta": 266
    },
    {
      "season": "1980-81",
      "team": "MIL",
      "gp": 77,
      "min": 2215.0,
      "pts": 1290,
      "reb": 289,
      "ast": 234,
      "stl": 88,
      "blk": 28,
      "tov": 150,
      "pf": 182,
      "fgm": 537,
      "fga": 1102,
      "fg3m": 3,
      "fg3a": 21,
      "ftm": 213,
      "fta": 241
    },
    {
      "season": "1981-82",
      "team": "MIL",
      "gp": 41,
      "min": 924.0,
      "pts": 511,
      "reb": 125,
      "ast": 109,
      "stl": 28,
      "blk": 3,
      "tov": 64,
      "pf": 91,
      "fgm": 209,
      "fga": 433,
      "fg3m": 4,
      "fg3a": 9,
      "ftm": 89,
      "fta": 103
    },
    {
      "season": "1982-83",
      "team": "MIL",
      "gp": 70,
      "min": 1855.0,
      "pts": 1007,
      "reb": 246,
      "ast": 207,
      "stl": 40,
      "blk": 9,
      "tov": 122,
      "pf": 155,
      "fgm": 421,
      "fga": 856,
      "fg3m": 1,
      "fg3a": 13,
      "ftm": 164,
      "fta": 196
    },
    {
      "season": "1983-84",
      "team": "MIL",
      "gp": 81,
      "min": 2431.0,
      "pts": 1220,
      "reb": 332,
      "ast": 265,
      "stl": 53,
      "blk": 14,
      "tov": 148,
      "pf": 224,
      "fgm": 509,
      "fga": 1094,
      "fg3m": 6,
      "fg3a": 31,
      "ftm": 196,
      "fta": 243
    },
    {
      "season": "1984-85",
      "team": "LAC",
      "gp": 80,
      "min": 2042.0,
      "pts": 1115,
      "reb": 230,
      "ast": 171,
      "stl": 47,
      "blk": 18,
      "tov": 116,
      "pf": 128,
      "fgm": 460,
      "fga": 990,
      "fg3m": 14,
      "fg3a": 39,
      "ftm": 181,
      "fta": 206
    },
    {
      "season": "1985-86",
      "team": "LAC",
      "gp": 58,
      "min": 1161.0,
      "pts": 510,
      "reb": 123,
      "ast": 108,
      "stl": 31,
      "blk": 8,
      "tov": 68,
      "pf": 81,
      "fgm": 199,
      "fga": 451,
      "fg3m": 6,
      "fg3a": 18,
      "ftm": 106,
      "fta": 119
    },
    {
      "season": "1986-87",
      "team": "MIL",
      "gp": 34,
      "min": 418.0,
      "pts": 175,
      "reb": 52,
      "ast": 35,
      "stl": 10,
      "blk": 2,
      "tov": 15,
      "pf": 50,
      "fgm": 79,
      "fga": 171,
      "fg3m": 1,
      "fg3a": 6,
      "ftm": 16,
      "fta": 20
    }
  ]
}