{
  "id": 76497,
  "name": "Quintin Dailey",
  "seasons": [
    {
      "season": "1982-83",
      "team": "CHI",
      "gp": 76,
      "min": 2081.0,
      "pts": 1151,
      "reb": 260,
      "ast": 280,
      "stl": 72,
      "blk": 10,
      "tov": 205,
      "pf": 248,
      "fgm": 470,
      "fga": 1008,
      "fg3m": 5,
      "fg3a": 25,
      "ftm": 206,
      "fta": 282
    },
    {
      "season": "1983-84",
      "team": "CHI",
      "gp": 82,
      "min": 2449.0,
      "pts": 1491,
      "reb": 235,
      "ast": 254,
      "stl": 109,
      "blk": 11,
      "tov": 220,
      "pf": 218,
      "fgm": 583,
      "fga": 1229,
      "fg3m": 4,
      "fg3a": 32,
      "ftm": 321,
      "fta": 396
    },
    {
      "season": "1984-85",
      "team": "CHI",
      "gp": 79,
      "min": 2101.0,
      "pts": 1262,
      "reb": 208,
      "ast": 191,
      "stl": 71,
      "blk": 5,
      "tov": 154,
      "pf": 192,
      "fgm": 525,
      "fga": 1111,
      "fg3m": 7,
      "fg3a": 30,
      "ftm": 205,
      "fta": 251
    },
    {
      "season": "1985-86",
      "team": "CHI",
      "gp": 35,
      "min": 723.0,
      "pts": 569,
      "reb": 68,
      "ast": 67,
      "stl": 22,
      "blk": 5,
      "tov": 67,
      "pf": 86,
      "fgm": 203,
      "fga": 470,
      "fg3m": 0,
      "fg3a": 8,
      "ftm": 163,
      "fta": 198
    },
    {
      "season": "1986-87",
      "team": "LAC",
      "gp": 49,
      "min": 924.0,
      "pts": 520,
      "reb": 83,
      "ast": 79,
      "stl": 43,
      "blk": 8,
      "tov": 71,
      "pf": 113,
      "fgm": 200,
      "fga": 491,
      "fg3m": 1,
      "fg3a": 10,
      "ftm": 119,
      "fta": 155
    },
    {
      "season": "1987-88",
      "team": "LAC",
      "gp": 67,
      "min": 1282.0,
      "pts": 901,
      "reb": 154,
      "ast": 109,
      "stl": 69,
      "blk": 4,
      "tov": 123,
      "pf": 128,
      "fgm": 328,
      "fga": 755,
      "fg3m": 2,
      "fg3a": 12,
      "ftm": 243,
      "fta": 313
    },
    {
      "season": "1988-89",
      "team": "LAC",
      "gp": 69,
      "min": 1722.0,
      "pts": 1114,
      "reb": 204,
      "ast": 154,
      "stl": 90,
      "blk": 6,
      "tov": 122,
      "pf": 152,
      "fgm": 448,
      "fga": 964,
      "fg3m": 1,
      "fg3a": 9,
      "ftm": 217,
      "fta": 286
    },
    {
      "season": "1989-90",
      "team": "SEA",
      "gp": 30,
      "min": 491.0,
      "pts": 247,
      "reb": 51,
      "ast": 34,
      "stl": 12,
      "blk": 0,
      "tov": 34,
      "pf": 63,
      "fgm": 97,
      "fga": 240,
      "fg3m": 1,
      "fg3a": 5,
      "ftm": 52,
      "fta": 66
    },
    {
      "season": "1990-91",
      "team": "SEA",
      "gp": 30,
      "min": 299.0,
      "pts": 184,
      "reb": 32,
      "ast": 16,
      "stl": 7,
      "blk": 1,
      "tov": 19,
      "pf": 25,
      "fgm": 73,
      "fga": 155,
      "fg3m": 0,
      "fg3a": 1,
      "ftm": 38,
      "fta": 62
    },
    {
      "season": "1991-92",
      "team": "SEA",
      "gp": 11,
      "min": 98.0,
      "pts": 31,
      "reb": 12,
      "ast": 4,
      "stl": 5,
      "blk": 1,
      "tov": 10,
      "pf": 6,
      "fgm": 9,
      "fga": 37,
      "fg3m": 0,
      "fg3a": 1,
      "ftm": 13,
      "fta": 16
    }
  ]
}