{
  "id": 76752,
  "name": "Anthony Frederick",
  "seasons": [
    {
      "season": "1988-89",
      "team": "IND",
      "gp": 46,
      "min": 313.0,
      "pts": 152,
      "reb": 52,
      "ast": 20,
      "stl": 14,
      "blk": 6,
      "tov": 34,
      "pf": 59,
      "fgm": 63,
      "fga": 125,
      "fg3m": 2,
      "fg3a": 5,
      "ftm": 24,
      "fta": 34
    },
    {
      "season": "1990-91",
      "team": "SAC",
      "gp": 35,
      "min": 475.0,
      "pts": 177,
      "reb": 84,
      "ast": 44,
      "stl": 22,
      "blk": 13,
      "tov": 40,
      "pf": 50,
      "fgm": 67,
      "fga": 168,
      "fg3m": 0,
      "fg3a": 0,
      "ftm": 43,
      "fta": 60
    },
    {
      "season": "1991-92",
      "team": "CHH",
      "gp": 66,
      "min": 852.0,
      "pts": 389,
      "reb": 144,
      "ast": 71,
      "stl": 40,
      "blk": 26,
      "tov": 58,
      "pf": 91,
      "fgm": 161,
      "fga": 370,
      "fg3m": 4,
      "fg3a": 17,
      "ftm": 63,
      "fta": 92
    }
  ]
}