{
  "id": 78178,
  "name": "Adrian Smith",
  "seasons": [
    {
      "season": "1961-62",
      "team": "CIN",
      "gp": 80,
      "min": 1462.0,
      "pts": 576,
      "reb": 151,
      "ast": 167,
      "stl": 0,
      "blk": 0,
      "tov": 0,
      "pf": 101,
      "fgm": 202,
      "fga": 499,
      "fg3m": 0,
      "fg3a": 0,
      "ftm": 172,
      "fta": 222
    },
    {
      "season": "1962-63",
      "team": "CIN",
      "gp": 79,
      "min": 1522.0,
      "pts": 705,
      "reb": 174,
      "ast": 141,
      "stl": 0,
      "blk": 0,
      "tov": 0,
      "pf": 157,
      "fgm": 241,
      "fga": 544,
      "fg3m": 0,
      "fg3a": 0,
      "ftm": 223,
      "fta": 275
    },
    {
      "season": "1963-64",
      "team": "CIN",
      "gp": 66,
      "min": 1524.0,
      "pts": 622,
      "reb": 147,
      "ast": 145,
      "stl": 0,
      "blk": 0,
      "tov": 0,
      "pf": 164,
      "fgm": 234,
      "fga": 576,
      "fg3m": 0,
      "fg3a": 0,
      "ftm": 154,
      "fta": 197
    },
    {
      "season": "1964-65",
      "team": "CIN",
      "gp": 80,
      "min": 2745.0,
      "pts": 1210,
      "reb": 220,
      "ast": 240,
      "stl": 0,
      "blk": 0,
      "tov": 0,
      "pf": 199,
      "fgm": 463,
      "fga": 1016,
      "fg3m": 0,
      "fg3a": 0,
      "ftm": 284,
      "fta": 342
    },
    {
      "season": "1965-66",
      "team": "CIN",
      "gp": 80,
      "min": 2982.0,
      "pts": 1470,
      "reb": 287,
      "ast": 256,
      "stl": 0,
      "blk": 0,
      "tov": 0,
      "pf": 276,
      "fgm": 531,
      "fga": 1310,
      "fg3m": 0,
      "fg3a": 0,
      "ftm": 408,
      "fta": 480
    },
    {
      "season": "1966-67",
      "team": "CIN",
      "gp": 81,
      "min": 2636.0,
      "pts": 1347,
      "reb": 205,
      "ast": 187,
      "stl": 0,
      "blk": 0,
      "tov": 0,
      "pf": 272,
      "fgm": 502,
      "fga": 1147,
      "fg3m": 0,
      "fg3a": 0,
      "ftm": 343,
      "fta": 380
    },
    {
      "season": "1967-68",
      "team": "CIN",
      "gp": 82,
      "min": 2783.0,
      "pts": 1280,
      "reb": 185,
      "ast": 272,
      "stl": 0,
      "blk": 0,
      "tov": 0,
      "pf": 259,
      "fgm": 480,
      "fga": 1035,
      "fg3m": 0,
      "fg3a": 0,
      "ftm": 320,
      "fta": 386
    },
    {
      "season": "1968-69",
      "team": "CIN",
      "gp": 73,
      "min": 1336.0,
      "pts": 703,
      "reb": 105,
      "ast": 127,
      "stl": 0,
      "blk": 0,
      "tov": 0,
      "pf": 166,
      "fgm": 243,
      "fga": 562,
      "fg3m": 0,
      "fg3a": 0,
      "ftm": 217,
      "fta": 269
    },
    {
      "season": "1970-71",
      "team": "SFW",
      "gp": 21,
      "min": 247.0,
      "pts": 111,
      "reb": 24,
      "ast": 30,
      "stl": 0,
      "blk": 0,
      "tov": 0,
      "pf": 24,
      "fgm": 38,
      "fga": 89,
      "fg3m": 0,
      "fg3a": 0,
      "ftm": 35,
      "fta": 41
    }
  ]
}