{
  "id": 78217,
  "name": "Mike Sojourner",
  "seasons": [
    {
      "season": "1974-75",
      "team": "ATL",
      "gp": 73,
      "min": 2129.0,
      "pts": 851,
      "reb": 642,
      "ast": 93,
      "stl": 35,
      "blk": 57,
      "tov": 0,
      "pf": 217,
      "fgm": 378,
      "fga": 775,
      "fg3m": 0,
      "fg3a": 0,
      "ftm": 95,
      "fta": 146
    },
    {
      "season": "1975-76",
      "team": "ATL",
      "gp": 67,
      "min": 1602.0,
      "pts": 576,
      "reb": 449,
      "ast": 58,
      "stl": 38,
      "blk": 40,
      "tov": 0,
      "pf": 174,
      "fgm": 248,
      "fga": 524,
      "fg3m": 0,
      "fg3a": 0,
      "ftm": 80,
      "fta": 119
    },
    {
      "season": "1976-77",
      "team": "ATL",
      "gp": 51,
      "min": 551.0,
      "pts": 231,
      "reb": 146,
      "ast": 21,
      "stl": 15,
      "blk": 9,
      "tov": 0,
      "pf": 66,
      "fgm": 95,
      "fga": 203,
      "fg3m": 0,
      "fg3a": 0,
      "ftm": 41,
      "fta": 57
    }
  ]
}