{
  "id": 967,
  "name": "Brian Evans",
  "seasons": [
    {
      "season": "1996-97",
      "team": "ORL",
      "gp": 14,
      "min": 57.0,
      "pts": 20,
      "reb": 8,
      "ast": 7,
      "stl": 1,
      "blk": 2,
      "tov": 2,
      "pf": 6,
      "fgm": 8,
      "fga": 22,
      "fg3m": 4,
      "fg3a": 8,
      "ftm": 0,
      "fta": 0
    },
    {
      "season": "1997-98",
      "team": "NJN",
      "gp": 72,
      "min": 893.0,
      "pts": 321,
      "reb": 137,
      "ast": 55,
      "stl": 29,
      "blk": 13,
      "tov": 38,
      "pf": 101,
      "fgm": 123,
      "fga": 312,
      "fg3m": 29,
      "fg3a": 87,
      "ftm": 46,
      "fta": 57
    },
    {
      "season": "1998-99",
      "team": "MIN",
      "gp": 16,
      "min": 145.0,
      "pts": 34,
      "reb": 19,
      "ast": 15,
      "stl": 5,
      "blk": 3,
      "tov": 2,
      "pf": 8,
      "fgm": 13,
      "fga": 44,
      "fg3m": 4,
      "fg3a": 13,
      "ftm": 4,
      "fta": 4
    }
  ]
}